CRR2_RWA/CRR2_RWA.py
CRR2_RWA/__init__.py
CRR2_RWA-1.0.dist-info/LICENSE
CRR2_RWA-1.0.dist-info/METADATA
CRR2_RWA-1.0.dist-info/WHEEL
CRR2_RWA-1.0.dist-info/top_level.txt
CRR2_RWA-1.0.dist-info/RECORD
