Metadata-Version: 2.1
Name: CRR2-RWA
Version: 1.0
Summary: UNKNOWN
Home-page: UNKNOWN
License: UNKNOWN
Platform: UNKNOWN
